{
    "id": "ragnarmmo:fire_ball",
    "display_name": "Fire Ball",
    "category": "CLASS_ACTIVE",
    "tier": "FIRST",
    "usage": "ACTIVE",
    "progression": {
        "max_level": 10,
        "upgrade_cost": 1,
        "can_gain_xp": false,
        "can_upgrade_with_points": true
    },
    "costs": {
        "base_cost": 0,
        "cost_per_level": 0
    },
    "cooldown_ticks": 0,
    "cast_delay_ticks": 0,
    "cast_time_ticks": 0,
    "jobs": [
        "MAGE"
    ],
    "requirements": {
        "ragnarmmo:fire_bolt": 4
    },
    "ui": {
        "texture": "mage/mage_fire_ball",
        "grid_x": 0,
        "grid_y": 2
    },
    "reference": {
        "notes": "Fire Ball: 80%-170% MATK, 25 SP, 1.5 sec cast/skill delay at Lv1-5, 1.0 sec at Lv6-10."
    },
    "level_data": {
        "1": { "sp_cost": 25, "damage_percent": 80, "splash_ratio": 0.75, "splash_radius": 2.5, "burn_seconds": 3, "cast_time_ticks": 30, "cast_delay_ticks": 30, "cooldown_ticks": 0 },
        "2": { "sp_cost": 25, "damage_percent": 90, "splash_ratio": 0.75, "splash_radius": 2.5, "burn_seconds": 3, "cast_time_ticks": 30, "cast_delay_ticks": 30, "cooldown_ticks": 0 },
        "3": { "sp_cost": 25, "damage_percent": 100, "splash_ratio": 0.75, "splash_radius": 2.5, "burn_seconds": 3, "cast_time_ticks": 30, "cast_delay_ticks": 30, "cooldown_ticks": 0 },
        "4": { "sp_cost": 25, "damage_percent": 110, "splash_ratio": 0.75, "splash_radius": 2.5, "burn_seconds": 3, "cast_time_ticks": 30, "cast_delay_ticks": 30, "cooldown_ticks": 0 },
        "5": { "sp_cost": 25, "damage_percent": 120, "splash_ratio": 0.75, "splash_radius": 2.5, "burn_seconds": 3, "cast_time_ticks": 30, "cast_delay_ticks": 30, "cooldown_ticks": 0 },
        "6": { "sp_cost": 25, "damage_percent": 130, "splash_ratio": 0.75, "splash_radius": 2.5, "burn_seconds": 3, "cast_time_ticks": 20, "cast_delay_ticks": 20, "cooldown_ticks": 0 },
        "7": { "sp_cost": 25, "damage_percent": 140, "splash_ratio": 0.75, "splash_radius": 2.5, "burn_seconds": 3, "cast_time_ticks": 20, "cast_delay_ticks": 20, "cooldown_ticks": 0 },
        "8": { "sp_cost": 25, "damage_percent": 150, "splash_ratio": 0.75, "splash_radius": 2.5, "burn_seconds": 3, "cast_time_ticks": 20, "cast_delay_ticks": 20, "cooldown_ticks": 0 },
        "9": { "sp_cost": 25, "damage_percent": 160, "splash_ratio": 0.75, "splash_radius": 2.5, "burn_seconds": 3, "cast_time_ticks": 20, "cast_delay_ticks": 20, "cooldown_ticks": 0 },
        "10": { "sp_cost": 25, "damage_percent": 170, "splash_ratio": 0.75, "splash_radius": 2.5, "burn_seconds": 3, "cast_time_ticks": 20, "cast_delay_ticks": 20, "cooldown_ticks": 0 }
    },
    "effect_class": "com.etema.ragnarmmo.skills.job.mage.FireBallSkillEffect"
}
